README.md
setup.cfg
setup.py
ec2objects/__init__.py
ec2objects.egg-info/PKG-INFO
ec2objects.egg-info/SOURCES.txt
ec2objects.egg-info/dependency_links.txt
ec2objects.egg-info/requires.txt
ec2objects.egg-info/top_level.txt
ec2objects/ec2api/__init__.py
ec2objects/ec2api/images.py
ec2objects/ec2api/keypairs.py
ec2objects/ec2api/regions.py
ec2objects/ec2common/__init__.py
ec2objects/ec2common/ec2exceptions.py
ec2objects/ec2object/__init__.py
ec2objects/ec2object/image.py
ec2objects/ec2object/keypair.py
ec2objects/ec2object/region.py